{
    "floss": [
        {
            "name": "West Yorkshire Spinners ColourLab DK",
            "url": "https://www.ravelry.com/yarns/library/west-yorkshire-spinners-colourlab-dk",
            "colorways": [
                {
                    "hex": "#131114",
                    "name": "009 Phantom Black"
                },
                {
                    "hex": "#262E53",
                    "name": "111 True Blue"
                },
                {
                    "hex": "#908890",
                    "name": "137 Silver Grey"
                },
                {
                    "hex": "#B2A337",
                    "name": "186 Pear Green"
                },
                {
                    "hex": "#B2C135",
                    "name": "198 Lime Green"
                },
                {
                    "hex": "#F2A41C",
                    "name": "229 Citrus Yellow"
                },
                {
                    "hex": "#483D4B",
                    "name": "373 Stormy Grey"
                },
                {
                    "hex": "#870049",
                    "name": "539 Cerise Pink"
                },
                {
                    "hex": "#A20014",
                    "name": "556 Crimson Red"
                },
                {
                    "hex": "#BF004B",
                    "name": "647 Very Berry"
                },
                {
                    "hex": "#79C2BC",
                    "name": "705 Aqua Green"
                },
                {
                    "hex": "#006778",
                    "name": "716 Deep Teal"
                },
                {
                    "hex": "#914A93",
                    "name": "717 Thistle Purple"
                },
                {
                    "hex": "#171F5E",
                    "name": "764 Harbour Blue"
                }
            ]
        }
    ]
}
